Workbook

Sheet Statements
A1: P&L Statement
B2: 2013 | C2: 2014 | D2: 2015 | E2: 2016 | F2: 2017 | G2: 2018 | H2: 2019 | I2: 2020 | J2: 2021 | L2: Difference
A3: Revenue | D3: 8726 | E3: 12786 | F3: 40525 | G3: 103085 | H3: 176164 | I3: 260674 | J3: 437629 | L3: =G3-F3 -> 62560
A4: Cost of sales | D4: 2196 | E4: 4189 | F4: 10814 | G4: 29025 | H4: 58589 | I4: 83683 | J4: 143593
A5: Gross margin | D5: =D3-D4 -> 6530 | E5: =E3-E4 -> 8597 | F5: =F3-F4 -> 29711 | G5: =G3-G4 -> 74060 | H5: =H3-H4 -> 117575 | I5: =I3-I4 -> 176991 | J5: =J3-J4 -> 294036 | L5: =G5-F5 -> 44349
A6: Distribution costs | D6: 2164 | E6: 2759 | F6: 7660 | G6: 21438 | H6: 42045 | I6: 59994 | J6: 93184
A7: Admin expenses | D7: 3233 | E7: 4734 | F7: 13901 | G7: 35013 | H7: 56980 | I7: 86412 | J7: 139311 | L7: =G7-F7 -> 21112
A8: EBIT | D8: =D5-D6-D7 -> 1133 | E8: =E5-E6-E7 -> 1104 | F8: =F5-F6-F7 -> 8150 | G8: =G5-G6-G7 -> 17609 | H8: =H5-H6-H7 -> 18550 | I8: =I5-I6-I7 -> 30585 | J8: =J5-J6-J7 -> 61541 | L8: =G8-F8 -> 9459
A9: Interest | D9: -0.6 | E9: -0.2 | F9: 0 | G9: 41 | H9: =157-46 -> 111 | I9: 415 | J9: =426-1278 -> -852 | L9: =G9-F9 -> 41
A10: EBT | D10: =D8-D9 -> 1133.6 | E10: =E8-E9 -> 1104.2 | F10: =F8-F9 -> 8150 | G10: =G8-G9 -> 17568 | H10: =H8-H9 -> 18439 | I10: =I8-I9 -> 30170 | J10: =J8-J9 -> 62393
A11: Tax | D11: 284 | E11: 225 | F11: 1629 | G11: 3408 | H11: 3448 | I11: 5738 | J11: 13503 | L11: =G11-F11 -> 1779
A12: Net profit | D12: =D10-D11 -> 849.6 | E12: =E10-E11 -> 879.2 | F12: =F10-F11 -> 6521 | G12: =G10-G11 -> 14160 | H12: =H10-H11 -> 14991 | I12: =I10-I11 -> 24432 | J12: =J10-J11 -> 48890 | L12: =G12-F12 -> 7639
A13: Depreciation | B13: 2 | C13: 15 | D13: 71 | E13: 122 | F13: 174 | G13: 357 | H13: 869 | I13: 2021 | L13: =G13-F13 -> 183
A14: Amortization | D14: 3.5 | E14: 3.5 | G14: 96 | H14: 29 | I14: 587
A16: Balance Sheet
L17: Difference
A18: Cash | B18: 57 | C18: 994 | D18: 1026 | E18: 1729 | F18: 9327 | G18: 21073 | H18: 30224 | I18: 70377 | J18: 43325
A19: Accounts receivable | B19: 0.9 | C19: 92 | D19: 618 | E19: 1803 | F19: 3601 | G19: 6677 | H19: 12002 | I19: 8035 | J19: 58631 | L19: =G19-F19 -> 3076
A20: Inventory | B20: 125 | C20: 436 | D20: 960 | E20: 912 | F20: 1738 | G20: 12071 | H20: 22536 | I20: 28233 | J20: 60289 | L20: =G20-F20 -> 10333
A21: Current assets | B21: =B18+B19+B20 -> 182.9 | C21: =C18+C19+C20 -> 1522 | D21: =D18+D19+D20 -> 2604 | E21: =E18+E19+E20 -> 4444 | F21: =F18+F19+F20 -> 14666 | G21: =G18+G19+G20 -> 39821 | H21: =H18+H19+H20 -> 64762 | I21: =I18+I19+I20 -> 106645 | J21: =J18+J19+J20 -> 162245 | L21: =G21-F21 -> 25155
A22: Intangible assets | B22: 7 | C22: 7 | D22: 3.5 | E22: 0 | F22: 0 | G22: 330 | H22: 1337 | I22: 818 | J22: 187
A23: Tangible assets | B23: 5 | C23: 42 | D23: 354 | E23: 354 | F23: 723 | G23: 4179 | H23: 9543 | I23: 12959 | J23: 26133
A24: Fixed assets | B24: =B22+B23 -> 12 | C24: =C22+C23 -> 49 | D24: =D22+D23 -> 357.5 | E24: =E22+E23 -> 354 | F24: =F22+F23 -> 723 | G24: =G22+G23 -> 4509 | H24: =H22+H23 -> 10880 | I24: =I22+I23 -> 13777 | J24: =J22+J23 -> 26320 | L24: =G24-F24 -> 3786
A25: Total assets | B25: =B21+B24 -> 194.9 | C25: =C21+C24 -> 1571 | D25: =D21+D24 -> 2961.5 | E25: =E21+E24 -> 4798 | F25: =F21+F24 -> 15389 | G25: =G21+G24 -> 44330 | H25: =H21+H24 -> 75642 | I25: =I21+I24 -> 120422 | J25: =J21+J24 -> 188565 | L25: =G25-F25 -> 28941
A27: Cumulative depr & amort | B27: =B13+B14 -> 2 | C27: =B27+C13+C14 -> 17 | D27: =C27+D13+D14 -> 91.5 | E27: =D27+E13+E14 -> 217 | F27: =E27+F13+F14 -> 391 | G27: =F27+G13+G14 -> 844 | H27: =G27+H13+H14 -> 1742 | I27: =H27+I13+I14 -> 4350 | J27: =I27+J13+J14 -> 4350
A29: Accounts payable | B29: 104 | C29: 393 | D29: 985 | E29: 2112 | F29: 6276 | G29: 20020 | H29: 32373 | I29: 55889 | J29: 78466 | L29: =G29-F29 -> 13744
A30: Short-term debt | L30: =G30-F30 -> 0
A31: Accruals | D31: 71 | E31: 71 | F31: 72 | G31: 57 | H31: 26 | I31: 1022 | J31: 1186
A32: Current liabilities | B32: =B29+B30+B31 -> 104 | C32: =C29+C30+C31 -> 393 | D32: =D29+D30+D31 -> 1056 | E32: =E29+E30+E31 -> 2183 | F32: =F29+F30+F31 -> 6348 | G32: =G29+G30+G31 -> 20077 | H32: =H29+H30+H31 -> 32399 | I32: =I29+I30+I31 -> 56911 | J32: =J29+J30+J31 -> 79652 | L32: =G32-F32 -> 13729
A33: Long-term debt | F33: 0 | G33: 1053 | H33: 5052 | I33: 3488 | J33: 0 | L33: =G33-F33 -> 1053
A34: Total liabilities | B34: =B32+B33 -> 104 | C34: =C32+C33 -> 393 | D34: =D32+D33 -> 1056 | E34: =E32+E33 -> 2183 | F34: =F32+F33 -> 6348 | G34: =G32+G33 -> 21130 | H34: =H32+H33 -> 37451 | I34: =I32+I33 -> 60399 | J34: =J32+J33 -> 79652 | L34: =G34-F34 -> 14782
A36: Share capital | B36: 0.002 | C36: 0.002 | D36: 0.002 | E36: 0.002 | F36: 0.002 | G36: 0.002 | H36: 0.002 | I36: 0.002 | J36: 0.002 | L36: =G36-F36 -> 0
A37: Retained earnings | B37: 90 | C37: 1178 | D37: 1906 | E37: 2615 | F37: 9041 | G37: 23200 | H37: 38191 | I37: 60023 | J37: 108913 | L37: =G37-F37 -> 14159
A38: Total equity | B38: =B36+B37 -> 90.002 | C38: =C36+C37 -> 1178.002 | D38: =D36+D37 -> 1906.002 | E38: =E36+E37 -> 2615.002 | F38: =F36+F37 -> 9041.002 | G38: =G36+G37 -> 23200.002 | H38: =H36+H37 -> 38191.002 | I38: =I36+I37 -> 60023.002 | J38: =J36+J37 -> 108913 | L38: =G38-F38 -> 14159
A40: Check | B40: =B38+B34-B25 -> -0.898 | C40: =C38+C34-C25 -> 0.002 | D40: =D38+D34-D25 -> 0.502 | E40: =E38+E34-E25 -> 0.002 | F40: =F38+F34-F25 -> 0.002 | G40: =G38+G34-G25 -> 0.002 | H40: =H38+H34-H25 -> 0.002 | I40: =I38+I34-I25 -> 0.002 | J40: =J38+J34-J25 -> 0.002
A43: COGS | D43: =D4/D3 -> 0.2516617 | E43: =E4/E3 -> 0.32762396 | F43: =F4/F3 -> 0.26684762 | G43: =G4/G3 -> 0.28156376 | H43: =H4/H3 -> 0.33258214 | I43: =I4/I3 -> 0.3210255 | J43: =J4/J3 -> 0.32811582
A44: Distrib costs | D44: =D6/D3 -> 0.2479945 | E44: =E6/E3 -> 0.21578289 | F44: =F6/F3 -> 0.18901912 | G44: =G6/G3 -> 0.2079643 | H44: =H6/H3 -> 0.23866965 | I44: =I6/I3 -> 0.23014954 | J44: =J6/J3 -> 0.21292922
A45: Admin expenses | D45: =D7/D3 -> 0.37050195 | E45: =E7/E3 -> 0.37024871 | F45: =F7/F3 -> 0.34302283 | G45: =G7/G3 -> 0.33965174 | H45: =H7/H3 -> 0.3234486 | I45: =I7/I3 -> 0.33149451 | J45: =J7/J3 -> 0.31833128
A47: Operatin profit % | D47: =1-D43-D44-D45 -> 0.12984185 | E47: =1-E43-E44-E45 -> 0.086344439 | F47: =1-F43-F44-F45 -> 0.20111043 | G47: =1-G43-G44-G45 -> 0.1708202 | H47: =1-H43-H44-H45 -> 0.10529961 | I47: =1-I43-I44-I45 -> 0.11733046 | J47: =1-J43-J44-J45 -> 0.14062368
A49: Net profit % | D49: =D12/D3 -> 0.097364199 | E49: =E12/E3 -> 0.068762709 | F49: =F12/F3 -> 0.16091302 | G49: =G12/G3 -> 0.13736237 | H49: =H12/H3 -> 0.085096842 | I49: =I12/I3 -> 0.093726263 | J49: =J12/J3 -> 0.11171563

Sheet Overall
B1: 2015 | C1: 2016 | D1: 2017 | E1: 2018 | F1: 2019 | G1: 2020 | H1: 2021
A2: Equity | B2: =Statements!D38 -> 1906.002 | C2: =Statements!E38 -> 2615.002 | D2: =Statements!F38 -> 9041.002 | E2: =Statements!G38 -> 23200.002 | F2: =Statements!H38 -> 38191.002 | G2: =Statements!I38 -> 60023.002 | H2: =Statements!J38 -> 108913
A3: Net debt | B3: =Statements!D30+Statements!D33 -> 0 | C3: =Statements!E30+Statements!E33 -> 0 | D3: =Statements!F30+Statements!F33 -> 0 | E3: =Statements!G30+Statements!G33 -> 1053 | F3: =Statements!H30+Statements!H33 -> 5052 | G3: =Statements!I30+Statements!I33 -> 3488 | H3: =Statements!J30+Statements!J33 -> 0
A5: Total funding | B5: =B2+B3 -> 1906.002 | C5: =C2+C3 -> 2615.002 | D5: =D2+D3 -> 9041.002 | E5: =E2+E3 -> 24253.002 | F5: =F2+F3 -> 43243.002 | G5: =G2+G3 -> 63511.002 | H5: =H2+H3 -> 108913
A8: Working capital | B8: =Statements!D21-Statements!D32 -> 1548 | C8: =Statements!E21-Statements!E32 -> 2261 | D8: =Statements!F21-Statements!F32 -> 8318 | E8: =Statements!G21-Statements!G32 -> 19744 | F8: =Statements!H21-Statements!H32 -> 32363 | G8: =Statements!I21-Statements!I32 -> 49734 | H8: =Statements!J21-Statements!J32 -> 82593
A9: Other capital | B9: =Statements!D24 -> 357.5 | C9: =Statements!E24 -> 354 | D9: =Statements!F24 -> 723 | E9: =Statements!G24 -> 4509 | F9: =Statements!H24 -> 10880 | G9: =Statements!I24 -> 13777 | H9: =Statements!J24 -> 26320
A11: Net operating assets | B11: =B8+B9 -> 1905.5 | C11: =C8+C9 -> 2615 | D11: =D8+D9 -> 9041 | E11: =E8+E9 -> 24253 | F11: =F8+F9 -> 43243 | G11: =G8+G9 -> 63511 | H11: =H8+H9 -> 108913
A13: Revenue | B13: =Statements!D3 -> 8726 | C13: =Statements!E3 -> 12786 | D13: =Statements!F3 -> 40525 | E13: =Statements!G3 -> 103085 | F13: =Statements!H3 -> 176164 | G13: =Statements!I3 -> 260674 | H13: =Statements!J3 -> 437629
A14: EBIT | B14: =Statements!D8 -> 1133 | C14: =Statements!E8 -> 1104 | D14: =Statements!F8 -> 8150 | E14: =Statements!G8 -> 17609 | F14: =Statements!H8 -> 18550 | G14: =Statements!I8 -> 30585 | H14: =Statements!J8 -> 61541
A16: Return on assets | B16: =B14/B11 -> 0.59459459 | C16: =C14/C11 -> 0.42217973 | D16: =D14/D11 -> 0.90144895 | E16: =E14/E11 -> 0.72605451 | F16: =F14/F11 -> 0.42897116 | G16: =G14/G11 -> 0.48157012 | H16: =H14/H11 -> 0.56504733
A17: Profitability | B17: =B14/B13 -> 0.12984185 | C17: =C14/C13 -> 0.086344439 | D17: =D14/D13 -> 0.20111043 | E17: =E14/E13 -> 0.1708202 | F17: =F14/F13 -> 0.10529961 | G17: =G14/G13 -> 0.11733046 | H17: =H14/H13 -> 0.14062368
A18: Asset turnover | B18: =B13/B11 -> 4.5793755 | C18: =C13/C11 -> 4.8894837 | D18: =D13/D11 -> 4.4823581 | E18: =E13/E11 -> 4.250402 | F18: =F13/F11 -> 4.0738154 | G18: =G13/G11 -> 4.1043914 | H18: =H13/H11 -> 4.0181521
A19: Leverage | B19: =B11/B2 -> 0.99973662 | C19: =C11/C2 -> 0.99999924 | D19: =D11/D2 -> 0.99999978 | E19: =E11/E2 -> 1.0453878 | F19: =F11/F2 -> 1.1322824 | G19: =G11/G2 -> 1.058111 | H19: =H11/H2 -> 0.99999998

Sheet WorkCap
B1: 2015 | C1: 2016 | D1: 2017 | E1: 2018 | F1: 2019 | G1: 2020 | H1: 2021
A2: Daily revenue | B2: =Statements!D3/365 -> 23.906849 | C2: =Statements!E3/365 -> 35.030137 | D2: =Statements!F3/365 -> 111.0274 | E2: =Statements!G3/365 -> 282.42466 | F2: =Statements!H3/365 -> 482.6411 | G2: =Statements!I3/365 -> 714.17534 | H2: =Statements!J3/365 -> 1198.9836
A3: Daily cost | B3: =Statements!D4/365 -> 6.0164384 | C3: =Statements!E4/365 -> 11.476712 | D3: =Statements!F4/365 -> 29.627397 | E3: =Statements!G4/365 -> 79.520548 | F3: =Statements!H4/365 -> 160.51781 | G3: =Statements!I4/365 -> 229.26849 | H3: =Statements!J4/365 -> 393.40548
A5: Receivables days | B5: =Statements!D19/WorkCap!B2 -> 25.850332 | C5: =Statements!E19/WorkCap!C2 -> 51.469967 | D5: =Statements!F19/WorkCap!D2 -> 32.433436 | E5: =Statements!G19/WorkCap!E2 -> 23.641703 | F5: =Statements!H19/WorkCap!F2 -> 24.86734 | G5: =Statements!I19/WorkCap!G2 -> 11.250738 | H5: =Statements!J19/WorkCap!H2 -> 48.900587
A6: Inventory days | B6: =Statements!D20/WorkCap!B3 -> 159.56284 | C6: =Statements!E20/WorkCap!C3 -> 79.465266 | D6: =Statements!F20/WorkCap!D3 -> 58.66192 | E6: =Statements!G20/WorkCap!E3 -> 151.79724 | F6: =Statements!H20/WorkCap!F3 -> 140.39564 | G6: =Statements!I20/WorkCap!G3 -> 123.14383 | H6: =Statements!J20/WorkCap!H3 -> 153.24901
A7: Payable days | B7: =Statements!D29/WorkCap!B3 -> 163.71812 | C7: =Statements!E29/WorkCap!C3 -> 184.02483 | D7: =Statements!F29/WorkCap!D3 -> 211.83096 | E7: =Statements!G29/WorkCap!E3 -> 251.75883 | F7: =Statements!H29/WorkCap!F3 -> 201.67856 | G7: =Statements!I29/WorkCap!G3 -> 243.77096 | H7: =Statements!J29/WorkCap!H3 -> 199.45325
A9: Cash cycle days | B9: =B5+B6-B7 -> 21.69505 | C9: =C5+C6-C7 -> -53.089594 | D9: =D5+D6-D7 -> -120.7356 | E9: =E5+E6-E7 -> -76.319881 | F9: =F5+F6-F7 -> -36.41558 | G9: =G5+G6-G7 -> -109.37639 | H9: =H5+H6-H7 -> 2.6963501
A11: Working capital as % of revenue | B11: =Overall!B8/Overall!B13 -> 0.17740087 | C11: =Overall!C8/Overall!C13 -> 0.17683404 | D11: =Overall!D8/Overall!D13 -> 0.20525601 | E11: =Overall!E8/Overall!E13 -> 0.19153126 | F11: =Overall!F8/Overall!F13 -> 0.1837095 | G11: =Overall!G8/Overall!G13 -> 0.19079003 | H11: =Overall!H8/Overall!H13 -> 0.18872835
A12: Gross margin | B12: =Statements!D5/Statements!D3 -> 0.7483383 | C12: =Statements!E5/Statements!E3 -> 0.67237604 | D12: =Statements!F5/Statements!F3 -> 0.73315238 | E12: =Statements!G5/Statements!G3 -> 0.71843624 | F12: =Statements!H5/Statements!H3 -> 0.66741786 | G12: =Statements!I5/Statements!I3 -> 0.6789745 | H12: =Statements!J5/Statements!J3 -> 0.67188418
A14: Marginal cash flow | B14: =B12-B11 -> 0.57093743 | C14: =C12-C11 -> 0.495542 | D14: =D12-D11 -> 0.52789636 | E14: =E12-E11 -> 0.52690498 | F14: =F12-F11 -> 0.48370836 | G14: =G12-G11 -> 0.48818448 | H14: =H12-H11 -> 0.48315582
A16: Net profit | B16: =Statements!D37-Statements!C37 -> 728 | C16: =Statements!E37-Statements!D37 -> 709 | D16: =Statements!F37-Statements!E37 -> 6426 | E16: =Statements!G37-Statements!F37 -> 14159 | F16: =Statements!H37-Statements!G37 -> 14991 | G16: =Statements!I37-Statements!H37 -> 21832 | H16: =Statements!J37-Statements!I37 -> 48890
A17: Depreciation & amortization | B17: =Statements!D13+Statements!D14 -> 74.5 | C17: =Statements!E13+Statements!E14 -> 125.5 | D17: =Statements!F13+Statements!F14 -> 174 | E17: =Statements!G13+Statements!G14 -> 453 | F17: =Statements!H13+Statements!H14 -> 898 | G17: =Statements!I13+Statements!I14 -> 2608 | H17: =Statements!J13+Statements!J14 -> 0
A18: Change in receivables | B18: =Statements!C19-Statements!D19 -> -526 | C18: =Statements!D19-Statements!E19 -> -1185 | D18: =Statements!E19-Statements!F19 -> -1798 | E18: =Statements!F19-Statements!G19 -> -3076 | F18: =Statements!G19-Statements!H19 -> -5325 | G18: =Statements!H19-Statements!I19 -> 3967 | H18: =Statements!I19-Statements!J19 -> -50596
A19: Change in inventory | B19: =-Statements!D20+Statements!C20 -> -524 | C19: =-Statements!E20+Statements!D20 -> 48 | D19: =-Statements!F20+Statements!E20 -> -826 | E19: =-Statements!G20+Statements!F20 -> -10333 | F19: =-Statements!H20+Statements!G20 -> -10465 | G19: =-Statements!I20+Statements!H20 -> -5697 | H19: =-Statements!J20+Statements!I20 -> -32056
A20: Change in payables | B20: =Statements!D29-Statements!C29 -> 592 | C20: =Statements!E29-Statements!D29 -> 1127 | D20: =Statements!F29-Statements!E29 -> 4164 | E20: =Statements!G29-Statements!F29 -> 13744 | F20: =Statements!H29-Statements!G29 -> 12353 | G20: =Statements!I29-Statements!H29 -> 23516 | H20: =Statements!J29-Statements!I29 -> 22577
A21: Change in accruals | B21: =Statements!D31-Statements!C31 -> 71 | C21: =Statements!E31-Statements!D31 -> 0 | D21: =Statements!F31-Statements!E31 -> 1 | E21: =Statements!G31-Statements!F31 -> -15 | F21: =Statements!H31-Statements!G31 -> -31 | G21: =Statements!I31-Statements!H31 -> 996 | H21: =Statements!J31-Statements!I31 -> 164
A22: Investing | B22: =Statements!C24-Statements!D24+Statements!C27-Statements!D27 -> -383 | C22: =Statements!D24-Statements!E24+Statements!D27-Statements!E27 -> -122 | D22: =Statements!E24-Statements!F24+Statements!E27-Statements!F27 -> -543 | E22: =Statements!F24-Statements!G24+Statements!F27-Statements!G27 -> -4239 | F22: =Statements!G24-Statements!H24+Statements!G27-Statements!H27 -> -7269 | G22: =Statements!H24-Statements!I24+Statements!H27-Statements!I27 -> -5505 | H22: =Statements!I24-Statements!J24+Statements!I27-Statements!J27 -> -12543
A23: Financing | B23: =Statements!D30+Statements!D33-Statements!C30-Statements!C33 -> 0 | C23: =Statements!E30+Statements!E33-Statements!D30-Statements!D33 -> 0 | D23: =Statements!F30+Statements!F33-Statements!E30-Statements!E33 -> 0 | E23: =Statements!G30+Statements!G33-Statements!F30-Statements!F33 -> 1053 | F23: =Statements!H30+Statements!H33-Statements!G30-Statements!G33 -> 3999 | G23: =Statements!I30+Statements!I33-Statements!H30-Statements!H33 -> -1564 | H23: =Statements!J30+Statements!J33-Statements!I30-Statements!I33 -> -3488
A25: Net cash | B25: =SUM(B16:B23) -> 32.5 | C25: =SUM(C16:C23) -> 702.5 | D25: =SUM(D16:D23) -> 7598 | E25: =SUM(E16:E23) -> 11746 | F25: =SUM(F16:F23) -> 9151 | G25: =SUM(G16:G23) -> 40153 | H25: =SUM(H16:H23) -> -27052
A27: Cash change | B27: =Statements!D18-Statements!C18 -> 32 | C27: =Statements!E18-Statements!D18 -> 703 | D27: =Statements!F18-Statements!E18 -> 7598 | E27: =Statements!G18-Statements!F18 -> 11746 | F27: =Statements!H18-Statements!G18 -> 9151 | G27: =Statements!I18-Statements!H18 -> 40153 | H27: =Statements!J18-Statements!I18 -> -27052
A29: Difference | B29: =B27-B25 -> -0.5 | C29: =C27-C25 -> 0.5 | D29: =D27-D25 -> 0 | E29: =E27-E25 -> 0 | F29: =F27-F25 -> 0 | G29: =G27-G25 -> 0 | H29: =H27-H25 -> 0

Sheet Levers
D1: Net cash flow | E1: EBIT
A2: Current position | D2: =WorkCap!E25 -> 11746 | E2: =Statements!G8 -> 17609
A4: Price increase | B4: 1 | C4: % | D4: =E4-B4/100*Statements!G19 -> 964.08 | E4: =B4/100*Statements!G3 -> 1030.85
A6: Volume increase | B6: 1 | C6: % | D6: =E6-B6/100*(Statements!G19+Statements!G20-Statements!G29) -> 753.32 | E6: =B6/100*Statements!G5 -> 740.6
A8: COGS reduction | B8: 1 | C8: % | D8: =E8+B8/100*(Statements!G20-Statements!G29) -> 210.76 | E8: =B8/100*Statements!G4 -> 290.25
A10: Overheads reduction | B10: 1 | C10: % | D10: =E10 -> 350.13 | E10: =B10/100*Statements!G7 -> 350.13
A12: Reduction in debtors days | B12: 1 | C12: days | D12: =WorkCap!E2 -> 282.42466
A14: Reduction in inventory days | B14: 1 | C14: days | D14: =WorkCap!E3 -> 79.520548
A16: Increase in creditor days | B16: 1 | C16: days | D16: =WorkCap!E3 -> 79.520548
A18: Overall effect | D18: =SUM(D4:D16) -> 2719.7558 | E18: =SUM(E4:E16) -> 2411.83
A20: New position | D20: =D2+D18 -> 14465.756 | E20: =E2+E18 -> 20020.83
